_vendor/__init__.py
_vendor/lark_schema_parser.py
_vendor/lark_schema_scan_parser.py
binaries/__init__.py
binaries/constants.py
binaries/platform.py
cli/__init__.py
cli/_node.py
cli/cli.py
cli/custom.py
cli/options.py
cli/prisma.py
cli/utils.py
cli/commands/__init__.py
cli/commands/dev.py
cli/commands/fetch.py
cli/commands/generate.py
cli/commands/version.py
engine/__init__.py
engine/_abstract.py
engine/_http.py
engine/_query.py
engine/abstract.py
engine/errors.py
engine/http.py
engine/query.py
engine/utils.py
generator/__init__.py
generator/errors.py
generator/filters.py
generator/generator.py
generator/jsonrpc.py
generator/models.py
generator/schema.py
generator/types.py
generator/utils.py
generator/_dsl_parser/__init__.py
generator/_dsl_parser/parser.py
generator/_dsl_parser/transformer.py
vf_db_client/__init__.py
vf_db_client/__main__.py
vf_db_client/_async_http.py
vf_db_client/_base_client.py
vf_db_client/_builder.py
vf_db_client/_compat.py
vf_db_client/_config.py
vf_db_client/_constants.py
vf_db_client/_fields.py
vf_db_client/_metrics.py
vf_db_client/_proxy.py
vf_db_client/_raw_query.py
vf_db_client/_registry.py
vf_db_client/_sync_http.py
vf_db_client/_transactions.py
vf_db_client/_types.py
vf_db_client/_typing.py
vf_db_client/actions.py
vf_db_client/bases.py
vf_db_client/client.py
vf_db_client/enums.py
vf_db_client/errors.py
vf_db_client/fields.py
vf_db_client/http.py
vf_db_client/http_abstract.py
vf_db_client/metadata.py
vf_db_client/models.py
vf_db_client/mypy.py
vf_db_client/partials.py
vf_db_client/setup.py
vf_db_client/testing.py
vf_db_client/types.py
vf_db_client/utils.py
vf_db_client/validator.py
vf_db_client-1.0.0.dist-info/METADATA
vf_db_client-1.0.0.dist-info/WHEEL
vf_db_client-1.0.0.dist-info/top_level.txt
vf_db_client-1.0.0.dist-info/RECORD
