Metadata-Version: 2.4
Name: vf-db-client
Version: 1.0.0
Requires-Dist: prisma-client-py>=0.7.0
Dynamic: requires-dist
